congrads/__init__.py
congrads/callbacks/base.py
congrads/callbacks/registry.py
congrads/checkpoints.py
congrads/constraints/base.py
congrads/constraints/registry.py
congrads/core/batch_runner.py
congrads/core/congradscore.py
congrads/core/constraint_engine.py
congrads/core/epoch_runner.py
congrads/datasets/registry.py
congrads/descriptor.py
congrads/metrics.py
congrads/networks/registry.py
congrads/py.typed
congrads/transformations/base.py
congrads/transformations/registry.py
congrads/utils/preprocessors.py
congrads/utils/utility.py
congrads/utils/validation.py
congrads-1.2.0.dist-info/WHEEL
congrads-1.2.0.dist-info/METADATA
congrads-1.2.0.dist-info/RECORD
