Metadata-Version: 2.3
Name: congrads
Version: 1.2.0
Summary: A toolbox for using Constraint Guided Gradient Descent when training neural networks.
Author: Wout Rombouts, Quinten Van Baelen, Peter Karsmakers
Author-email: Wout Rombouts <wout.rombouts@kuleuven.be>, Quinten Van Baelen <quinten.vanbaelen@kuleuven.be>, Peter Karsmakers <peter.karsmakers@kuleuven.be>
License: Copyright 2024 DTAI - KU Leuven
Requires-Dist: numpy>=1.24.0
Requires-Dist: pandas>=1.5.0
Requires-Dist: torch>=2.0.0
Requires-Dist: torchvision>=0.15.1
Requires-Dist: tqdm>=4.65.0
Requires-Dist: matplotlib>=3.7.0 ; extra == 'examples'
Requires-Dist: tensorboard>=2.18.0 ; extra == 'examples'
Requires-Python: >=3.11
Provides-Extra: examples
